{
	"info": {
		"_postman_id": "a1b2c3d4-e5f6-4a5b-b6c7-d8e9f0a1b2c3",
		"name": "Social Media API",
		"description": "API collection for the Social Media project, covering Authentication and User modules.",
		"schema": "https://schema.getpostman.com/json/collection/v2.1.0/collection.json"
	},
	"item": [
		{
			"name": "Auth",
			"item": [
				{
					"name": "Signup - Success",
					"request": {
						"method": "POST",
						"header": [],
						"body": {
							"mode": "raw",
							"raw": "{\n    \"username\": \"testuser\",\n    \"email\": \"test@example.com\",\n    \"password\": \"Password123\",\n    \"confirmPassword\": \"Password123\",\n    \"phone\": \"01234567890\",\n    \"age\": 25,\n    \"gender\": \"male\"\n}",
							"options": {
								"raw": {
									"language": "json"
								}
							}
						},
						"url": {
							"raw": "{{baseUrl}}/api/v1/auth/signup",
							"host": [
								"{{baseUrl}}"
							],
							"path": [
								"api",
								"v1",
								"auth",
								"signup"
							]
						}
					},
					"response": []
				},
				{
					"name": "Signup - Validation Error (Passwords don't match)",
					"request": {
						"method": "POST",
						"header": [],
						"body": {
							"mode": "raw",
							"raw": "{\n    \"username\": \"testuser\",\n    \"email\": \"test2@example.com\",\n    \"password\": \"Password123\",\n    \"confirmPassword\": \"WrongPassword\",\n    \"phone\": \"01234567890\",\n    \"age\": 25,\n    \"gender\": \"male\"\n}",
							"options": {
								"raw": {
									"language": "json"
								}
							}
						},
						"url": {
							"raw": "{{baseUrl}}/api/v1/auth/signup",
							"host": [
								"{{baseUrl}}"
							],
							"path": [
								"api",
								"v1",
								"auth",
								"signup"
							]
						}
					},
					"response": []
				},
				{
					"name": "Login - Success",
					"request": {
						"method": "POST",
						"header": [],
						"body": {
							"mode": "raw",
							"raw": "{\n    \"email\": \"test@example.com\",\n    \"password\": \"Password123\"\n}",
							"options": {
								"raw": {
									"language": "json"
								}
							}
						},
						"url": {
							"raw": "{{baseUrl}}/api/v1/auth/login",
							"host": [
								"{{baseUrl}}"
							],
							"path": [
								"api",
								"v1",
								"auth",
								"login"
							]
						}
					},
					"response": []
				},
				{
					"name": "Login - Invalid Credentials",
					"request": {
						"method": "POST",
						"header": [],
						"body": {
							"mode": "raw",
							"raw": "{\n    \"email\": \"test@example.com\",\n    \"password\": \"WrongPassword\"\n}",
							"options": {
								"raw": {
									"language": "json"
								}
							}
						},
						"url": {
							"raw": "{{baseUrl}}/api/v1/auth/login",
							"host": [
								"{{baseUrl}}"
							],
							"path": [
								"api",
								"v1",
								"auth",
								"login"
							]
						}
					},
					"response": []
				}
			]
		}
	],
	"event": [
		{
			"listen": "prerequest",
			"script": {
				"type": "text/javascript",
				"exec": [
					""
				]
			}
		},
		{
			"listen": "test",
			"script": {
				"type": "text/javascript",
				"exec": [
					""
				]
			}
		}
	],
	"variable": [
		{
			"key": "baseUrl",
			"value": "http://localhost:3000",
			"type": "string"
		}
	]
}
